cchardet/__init__.py
cchardet/_cchardet.cp38-win_amd64.pyd
cchardet/version.py
cchardet-2.1.6.data/scripts/cchardetect
cchardet-2.1.6.dist-info/COPYING
cchardet-2.1.6.dist-info/METADATA
cchardet-2.1.6.dist-info/WHEEL
cchardet-2.1.6.dist-info/top_level.txt
cchardet-2.1.6.dist-info/RECORD
