Metadata-Version: 1.1
Name: cchardet
Version: 2.1.6
Summary: cChardet is high speed universal character encoding detector.
Home-page: https://github.com/PyYoshi/cChardet
Author: PyYoshi
Author-email: myoshi321go@gmail.com
License: Mozilla Public License
Keywords: cython,chardet,charsetdetect
Platform: UNKNOWN
Classifier: License :: OSI Approved :: Mozilla Public License 1.1 (MPL 1.1)
Classifier: License :: OSI Approved :: GNU General Public License (GPL)
Classifier: License :: OSI Approved :: GNU Library or Lesser General Public License (LGPL)
Classifier: Programming Language :: Cython
Classifier: Programming Language :: Python
Classifier: Topic :: Software Development :: Libraries
Classifier: Programming Language :: Python :: 3
Classifier: Programming Language :: Python :: 3.5
Classifier: Programming Language :: Python :: 3.6
Classifier: Programming Language :: Python :: 3.7
Classifier: Programming Language :: Python :: 3.8
